BSD-LICENSE
MANIFEST.in
README.rst
setup.py
django_json_settings2.egg-info/PKG-INFO
django_json_settings2.egg-info/SOURCES.txt
django_json_settings2.egg-info/dependency_links.txt
django_json_settings2.egg-info/requires.txt
django_json_settings2.egg-info/top_level.txt
json_settings2/__init__.py
json_settings2/management/__init__.py
json_settings2/management/commands/__init__.py
json_settings2/management/commands/write_json_settings.py