Metadata-Version: 1.1
Name: django-json-settings2
Version: 0.1
Summary: Set, and save, Django settings to json formatted files.
Home-page: https://bitbucket.org/netlandish/django-json-settings2/
Author: Netlandish Inc.
Author-email: hello@netlandish.com
License: UNKNOWN
Platform: any
Classifier: Development Status :: 4 - Beta
Classifier: Intended Audience :: Developers
Classifier: Natural Language :: English
Classifier: Operating System :: OS Independent
Classifier: Programming Language :: Python
Classifier: Programming Language :: Python :: 3.6
Classifier: Programming Language :: Python :: 3.7
Classifier: Environment :: Web Environment
